gimmebio.seqtalk-0.3.0-py3.6-nspkg.pth
gimmebio/seqtalk/__init__.py
gimmebio/seqtalk/seq_data.py
gimmebio.seqtalk-0.3.0.dist-info/METADATA
gimmebio.seqtalk-0.3.0.dist-info/RECORD
gimmebio.seqtalk-0.3.0.dist-info/WHEEL
gimmebio.seqtalk-0.3.0.dist-info/namespace_packages.txt
gimmebio.seqtalk-0.3.0.dist-info/top_level.txt
